.gitignore
LICENSE.md
README.md
pyproject.toml
setup.cfg
src/pykxnr/__init__.py
src/pykxnr/colors.py
src/pykxnr/config.py
src/pykxnr/debug_logging.py
src/pykxnr/dict_tools.py
src/pykxnr/frozendict.py
src/pykxnr/matplotlib_tools.py
src/pykxnr/numpy_tools.py
src/pykxnr/progress_bar.py
src/pykxnr/scipy_tools.py
src/pykxnr/string_tools.py
src/pykxnr/utils.py
src/pykxnr.egg-info/PKG-INFO
src/pykxnr.egg-info/SOURCES.txt
src/pykxnr.egg-info/dependency_links.txt
src/pykxnr.egg-info/top_level.txt
tests/test_string_tools.py