Metadata-Version: 2.1
Name: pykxnr
Version: 0.0.2
Summary: A collection of tools that I (used to) reinvent for day to day use.
Home-page: https://github.com/kxnr/PyKxnr
Author: Connor Keane
Author-email: connor.keane@kxnr.me
License: UNKNOWN
Project-URL: Bug Tracker, https://github.com/kxnr/PyKxnr/issues
Platform: UNKNOWN
Classifier: Programming Language :: Python :: 3 :: Only
Classifier: License :: OSI Approved :: GNU General Public License v3 (GPLv3)
Classifier: Operating System :: OS Independent
Requires-Python: >=3.6
License-File: LICENSE.md
